{"nodes":[{"title":"Learn Dijkstra's Algorithm","id":"1","desc":"Overview of the steps to learn Dijkstra's Algorithm.","bgType":"rect","icon":"file","type":"node","index":10,"backgroundColor":"#0d09e1","iconColor":"#f5efef","borderColor":"#6e00b8","x":890.5,"y":100,"vy":0,"vx":0,"lastX":100,"lastY":466,"fx":890.5,"fy":100,"dx":889,"dy":99},{"title":"Understand Graph Theory Basics","id":"2","desc":"Learn the fundamental concepts of graph theory.","bgType":"rect","icon":"file","type":"node","index":5,"backgroundColor":"#0d09e1","iconColor":"#f5efef","borderColor":"#6e00b8","x":1013.5,"y":400,"vy":0,"vx":0,"lastX":500,"lastY":546,"fx":1013.5,"fy":400},{"title":"What is a Graph?","id":"2.1","desc":"Learn about vertices and edges in graph theory.","bgType":"rect","icon":"file","type":"node","index":3,"backgroundColor":"#0d09e1","iconColor":"#f5efef","borderColor":"#6e00b8","x":533.5,"y":700,"vy":0,"vx":0,"lastX":900,"lastY":66,"fx":533.5,"fy":700},{"title":"Types of Graphs","id":"2.2","desc":"Understand different types of graphs (directed, undirected, weighted, etc.).","bgType":"rect","icon":"file","type":"node","index":21,"backgroundColor":"#0d09e1","iconColor":"#f5efef","borderColor":"#6e00b8","x":1093.5,"y":700,"vy":0,"vx":0,"lastX":900,"lastY":866,"fx":1093.5,"fy":700},{"title":"Graph Representation","id":"2.3","desc":"Learn how graphs can be represented (adjacency list, adjacency matrix, etc.).","bgType":"rect","icon":"file","type":"node","index":12,"backgroundColor":"#0d09e1","iconColor":"#f5efef","borderColor":"#6e00b8","x":1493.5,"y":700,"vy":0,"vx":0,"lastX":900,"lastY":-14,"fx":1493.5,"fy":700},{"title":"Learn Dijkstra's Algorithm","id":"3","desc":"Understand the theory and application of Dijkstra's Algorithm.","bgType":"rect","icon":"file","type":"node","index":23,"backgroundColor":"#0d09e1","iconColor":"#f5efef","borderColor":"#6e00b8","x":693.5,"y":400,"vy":0,"vx":0,"lastX":500,"lastY":706,"fx":693.5,"fy":400},{"title":"Algorithm Overview","id":"3.1","desc":"Learn the basic idea and purpose of Dijkstra's Algorithm.","bgType":"rect","icon":"file","type":"node","index":14,"backgroundColor":"#0d09e1","iconColor":"#f5efef","borderColor":"#6e00b8","x":1413.5,"y":700,"vy":0,"vx":0,"lastX":900,"lastY":786,"fx":1413.5,"fy":700},{"title":"Algorithm Steps","id":"3.2","desc":"Understand the step-by-step process of the algorithm.","bgType":"rect","icon":"file","type":"node","index":22,"backgroundColor":"#0d09e1","iconColor":"#f5efef","borderColor":"#6e00b8","x":373.5,"y":700,"vy":0,"vx":0,"lastX":900,"lastY":1186,"fx":373.5,"fy":700},{"title":"Priority Queue","id":"3.3","desc":"Learn about the priority queue data structure used in the algorithm.","bgType":"rect","icon":"file","type":"node","index":6,"backgroundColor":"#0d09e1","iconColor":"#f5efef","borderColor":"#6e00b8","x":853.5,"y":700,"vy":0,"vx":0,"lastX":900,"lastY":-254,"fx":853.5,"fy":700},{"title":"Pseudocode","id":"3.4","desc":"Study the pseudocode of Dijkstra's Algorithm.","bgType":"rect","icon":"file","type":"node","index":24,"backgroundColor":"#0d09e1","iconColor":"#f5efef","borderColor":"#6e00b8","x":693.5,"y":700,"vy":0,"vx":0,"lastX":900,"lastY":146,"fx":693.5,"fy":700},{"title":"Implement Dijkstra's Algorithm","id":"4","desc":"Practice coding the algorithm in a programming language.","bgType":"rect","icon":"file","type":"node","index":15,"backgroundColor":"#0d09e1","iconColor":"#f5efef","borderColor":"#6e00b8","x":853.5,"y":400,"vy":0,"vx":0,"lastX":500,"lastY":386,"fx":853.5,"fy":400},{"title":"Choose a Language","id":"4.1","desc":"Select a programming language for implementation (e.g., Python, JavaScript, C++).","bgType":"rect","icon":"file","type":"node","index":4,"backgroundColor":"#0d09e1","iconColor":"#f5efef","borderColor":"#6e00b8","x":453.5,"y":700,"vy":0,"vx":0,"lastX":900,"lastY":-94,"fx":453.5,"fy":700},{"title":"Write the Code","id":"4.2","desc":"Implement the algorithm based on the pseudocode.","bgType":"rect","icon":"file","type":"node","index":18,"backgroundColor":"#0d09e1","iconColor":"#f5efef","borderColor":"#6e00b8","x":773.5,"y":700,"vy":0,"vx":0,"lastX":900,"lastY":306,"fx":773.5,"fy":700},{"title":"Test the Algorithm","id":"4.3","desc":"Test the implementation with various graph inputs.","bgType":"rect","icon":"file","type":"node","index":2,"backgroundColor":"#0d09e1","iconColor":"#f5efef","borderColor":"#6e00b8","x":1013.5,"y":700,"vy":0,"vx":0,"lastX":900,"lastY":1026,"fx":1013.5,"fy":700},{"title":"Optimize the Code","id":"4.4","desc":"Optimize the code for efficiency and readability.","bgType":"rect","icon":"file","type":"node","index":9,"backgroundColor":"#0d09e1","iconColor":"#f5efef","borderColor":"#6e00b8","x":933.5,"y":700,"vy":0,"vx":0,"lastX":900,"lastY":626,"fx":933.5,"fy":700},{"title":"Analyze Time Complexity","id":"5","desc":"Understand the time complexity of Dijkstra's Algorithm.","bgType":"rect","icon":"file","type":"node","index":19,"backgroundColor":"#0d09e1","iconColor":"#f5efef","borderColor":"#6e00b8","x":1093.5,"y":400,"vy":0,"vx":0,"lastX":500,"lastY":306,"fx":1093.5,"fy":400},{"title":"Big O Notation","id":"5.1","desc":"Learn about Big O notation and its significance.","bgType":"rect","icon":"file","type":"node","index":20,"backgroundColor":"#0d09e1","iconColor":"#f5efef","borderColor":"#6e00b8","x":1173.5,"y":700,"vy":0,"vx":0,"lastX":900,"lastY":226,"fx":1173.5,"fy":700},{"title":"Dijkstra's Complexity","id":"5.2","desc":"Analyze the time complexity of the algorithm.","bgType":"rect","icon":"file","type":"node","index":13,"backgroundColor":"#0d09e1","iconColor":"#f5efef","borderColor":"#6e00b8","x":1253.5,"y":700,"vy":0,"vx":0,"lastX":900,"lastY":1106,"fx":1253.5,"fy":700},{"title":"Applications of Dijkstra's Algorithm","id":"6","desc":"Explore real-world applications of Dijkstra's Algorithm.","bgType":"rect","icon":"file","type":"node","index":0,"backgroundColor":"#0d09e1","iconColor":"#f5efef","borderColor":"#6e00b8","x":773.5,"y":400,"vy":0,"vx":0,"lastX":500,"lastY":626,"fx":773.5,"fy":400},{"title":"Shortest Path Problems","id":"6.1","desc":"Understand how the algorithm is used to solve shortest path problems.","bgType":"rect","icon":"file","type":"node","index":11,"backgroundColor":"#0d09e1","iconColor":"#f5efef","borderColor":"#6e00b8","x":293.5,"y":700,"vy":0,"vx":0,"lastX":900,"lastY":946,"fx":293.5,"fy":700},{"title":"Network Routing","id":"6.2","desc":"Learn about its application in network routing protocols.","bgType":"rect","icon":"file","type":"node","index":8,"backgroundColor":"#0d09e1","iconColor":"#f5efef","borderColor":"#6e00b8","x":613.5,"y":700,"vy":0,"vx":0,"lastX":900,"lastY":466,"fx":613.5,"fy":700},{"title":"Geographical Mapping","id":"6.3","desc":"Explore its use in geographical mapping and GPS systems.","bgType":"rect","icon":"file","type":"node","index":17,"backgroundColor":"#0d09e1","iconColor":"#f5efef","borderColor":"#6e00b8","x":133.5,"y":700,"vy":0,"vx":0,"lastX":900,"lastY":-174,"fx":133.5,"fy":700},{"title":"Advanced Topics","id":"7","desc":"Study advanced topics related to Dijkstra's Algorithm.","bgType":"rect","icon":"file","type":"node","index":16,"backgroundColor":"#0d09e1","iconColor":"#f5efef","borderColor":"#6e00b8","x":933.5,"y":400,"vy":0,"vx":0,"lastX":500,"lastY":466,"fx":933.5,"fy":400},{"title":"A* Algorithm","id":"7.1","desc":"Learn about the A* algorithm as an extension of Dijkstra's Algorithm.","bgType":"rect","icon":"file","type":"node","index":1,"backgroundColor":"#0d09e1","iconColor":"#f5efef","borderColor":"#6e00b8","x":1333.5,"y":700,"vy":0,"vx":0,"lastX":900,"lastY":546,"fx":1333.5,"fy":700},{"title":"Bellman-Ford Algorithm","id":"7.2","desc":"Understand the differences between Dijkstra and Bellman-Ford algorithms.","bgType":"rect","icon":"file","type":"node","index":7,"backgroundColor":"#0d09e1","iconColor":"#f5efef","borderColor":"#6e00b8","x":1573.5,"y":700,"vy":0,"vx":0,"lastX":900,"lastY":706,"fx":1573.5,"fy":700},{"title":"Floyd-Warshall Algorithm","id":"7.3","desc":"Study the Floyd-Warshall algorithm for all-pairs shortest paths.","bgType":"rect","icon":"file","type":"node","index":25,"backgroundColor":"#0d09e1","iconColor":"#f5efef","borderColor":"#6e00b8","x":213.5,"y":700,"vy":0,"vx":0,"lastX":900,"lastY":386,"fx":213.5,"fy":700}],"links":[{"source":"1","target":"3","id":"2cwdG1peqCHOQTiCxF5Q7w76","x1":null,"y1":null,"x2":null,"y2":null,"type":"line","startIndex":1,"endIndex":3,"index":0},{"source":"5","target":"5.1","id":"3hZxYTStvH8D5MwXRbypXv2Y","x1":null,"y1":null,"x2":null,"y2":null,"type":"line","startIndex":1,"endIndex":3,"index":1},{"source":"1","target":"5","id":"4PpEnv4AtCQCzAqx7Ca71Y5e","x1":null,"y1":null,"x2":null,"y2":null,"type":"line","startIndex":1,"endIndex":3,"index":2},{"source":"3","target":"3.3","id":"AQubmulk5rL4Q7QYGQcXNNUj","x1":null,"y1":null,"x2":null,"y2":null,"type":"line","startIndex":1,"endIndex":3,"index":3},{"source":"1","target":"6","id":"KCQP4LAq7OFbrhOCs1YIujkA","x1":null,"y1":null,"x2":null,"y2":null,"type":"line","startIndex":1,"endIndex":3,"index":4},{"source":"4","target":"4.3","id":"MoQ3yQyHDmOd97eh2YddcDpz","x1":null,"y1":null,"x2":null,"y2":null,"type":"line","startIndex":1,"endIndex":3,"index":5},{"source":"2","target":"2.2","id":"NtY30V41VVljqJpbzWMjDYYP","x1":null,"y1":null,"x2":null,"y2":null,"type":"line","startIndex":1,"endIndex":3,"index":6},{"source":"7","target":"7.1","id":"Q3acwsWhBNNpSLTPY0s9oWld","x1":null,"y1":null,"x2":null,"y2":null,"type":"line","startIndex":1,"endIndex":3,"index":7},{"source":"4","target":"4.1","id":"QdFliD9vtJ24g6DzvOLpabaC","x1":null,"y1":null,"x2":null,"y2":null,"type":"line","startIndex":1,"endIndex":3,"index":8},{"source":"3","target":"3.1","id":"RUoGKgYC61FXNTc2r5BBsZmW","x1":null,"y1":null,"x2":null,"y2":null,"type":"line","startIndex":1,"endIndex":3,"index":9},{"source":"6","target":"6.3","id":"RZ6078OmdJsYvzIs98rpj4E0","x1":null,"y1":null,"x2":null,"y2":null,"type":"line","startIndex":1,"endIndex":3,"index":10},{"source":"1","target":"2","id":"SlmzWo9eb2XPTH2etjcqrTa9","x1":null,"y1":null,"x2":null,"y2":null,"type":"line","startIndex":1,"endIndex":3,"index":11},{"source":"3","target":"3.4","id":"UFTfjWq3GbBDjpEObVT699cD","x1":null,"y1":null,"x2":null,"y2":null,"type":"line","startIndex":1,"endIndex":3,"index":12},{"source":"7","target":"7.2","id":"UpHyW5bcfG7I1GZmShV65wTr","x1":null,"y1":null,"x2":null,"y2":null,"type":"line","startIndex":1,"endIndex":3,"index":13},{"source":"2","target":"2.1","id":"Xw3TIhfzXc5BVc4WAVmddw3B","x1":null,"y1":null,"x2":null,"y2":null,"type":"line","startIndex":1,"endIndex":3,"index":14},{"source":"2","target":"2.3","id":"YFaswa8uN1UZ80lEzMrrDe2f","x1":null,"y1":null,"x2":null,"y2":null,"type":"line","startIndex":1,"endIndex":3,"index":15},{"source":"5","target":"5.2","id":"YUVcrhAwMxVGHiUHZ97s1O8O","x1":null,"y1":null,"x2":null,"y2":null,"type":"line","startIndex":1,"endIndex":3,"index":16},{"source":"7","target":"7.3","id":"a7lDw4v92HSSYmAYrsbSlN2B","x1":null,"y1":null,"x2":null,"y2":null,"type":"line","startIndex":1,"endIndex":3,"index":17},{"source":"1","target":"4","id":"fAlCdpo6cXv389j1jzAASu9F","x1":null,"y1":null,"x2":null,"y2":null,"type":"line","startIndex":1,"endIndex":3,"index":18},{"source":"4","target":"4.4","id":"jz5JfXe9hYSI6hyKISXSy5jG","x1":null,"y1":null,"x2":null,"y2":null,"type":"line","startIndex":1,"endIndex":3,"index":19},{"source":"1","target":"7","id":"kjVX8VNWrNHeprJJmb5USLFH","x1":null,"y1":null,"x2":null,"y2":null,"type":"line","startIndex":1,"endIndex":3,"index":20},{"source":"6","target":"6.1","id":"pX3iFN7wFAAPoEklvoxE3kIg","x1":null,"y1":null,"x2":null,"y2":null,"type":"line","startIndex":1,"endIndex":3,"index":21},{"source":"3","target":"3.2","id":"rv1kv2beOYIw09IiEik4iWSQ","x1":null,"y1":null,"x2":null,"y2":null,"type":"line","startIndex":1,"endIndex":3,"index":22},{"source":"6","target":"6.2","id":"yBnkoWeCLIhPkApdwRpfPU1G","x1":null,"y1":null,"x2":null,"y2":null,"type":"line","startIndex":1,"endIndex":3,"index":23},{"source":"4","target":"4.2","id":"z4E9kfukObkmNB5C6qSqWLiV","x1":null,"y1":null,"x2":null,"y2":null,"type":"line","startIndex":1,"endIndex":3,"index":24}],"config":[{"key":"arrowEnd","value":true},{"key":"connectType","value":"poly"},{"key":"iconFillColor","value":"#0d09e1"},{"key":"layoutType","value":"treeVer"},{"key":"lineType","value":"dotted"},{"key":"nodeBorderColor","value":"#6e00b8"},{"key":"nodeIconColor","value":"#f5efef"},{"key":"strokeColor","value":"#4700cc"}]}