{"nodes":[{"title":"Linux Kernel Overview","id":"1","desc":"Introduction to the Linux kernel, its purpose, and its significance.","bgType":"rect","icon":"file","fx":853.5,"fy":100,"type":"node","index":0,"x":853.5,"y":100,"vy":0,"vx":0,"lastX":853.5,"lastY":100,"backgroundColor":"#05aee6","iconColor":"#f5f5f5","borderColor":"#0d7db5"},{"title":"Architecture of the Linux Kernel","id":"2","desc":"Detailed structure of the Linux kernel.","bgType":"rect","icon":"file","fx":853.5,"fy":300,"type":"node","index":1,"x":853.5,"y":300,"vy":0,"vx":0,"lastX":773.5,"lastY":340,"backgroundColor":"#05aee6","iconColor":"#f5f5f5","borderColor":"#0d7db5"},{"title":"Monolithic Kernel","id":"2.1","desc":"Explanation of the monolithic architecture of the Linux kernel.","bgType":"rect","icon":"file","fx":853.5,"fy":500,"type":"node","index":2,"x":853.5,"y":500,"vy":0,"vx":0,"lastX":533.5,"lastY":580,"backgroundColor":"#05aee6","iconColor":"#f5f5f5","borderColor":"#0d7db5"},{"title":"Kernel Space vs User Space","id":"2.2","desc":"Difference between kernel space and user space.","bgType":"rect","icon":"file","fx":933.5,"fy":500,"type":"node","index":3,"x":933.5,"y":500,"vy":0,"vx":0,"lastX":1173.5,"lastY":580,"backgroundColor":"#05aee6","iconColor":"#f5f5f5","borderColor":"#0d7db5"},{"title":"Kernel Mode","id":"2.2.1","desc":"Execution mode with full access to hardware.","bgType":"rect","icon":"file","fx":853.5,"fy":700,"type":"node","index":4,"x":853.5,"y":700,"vy":0,"vx":0,"lastX":1013.5,"lastY":820,"backgroundColor":"#05aee6","iconColor":"#f5f5f5","borderColor":"#0d7db5"},{"title":"User Mode","id":"2.2.2","desc":"Restricted execution mode for user applications.","bgType":"rect","icon":"file","fx":933.5,"fy":700,"type":"node","index":5,"x":933.5,"y":700,"vy":0,"vx":0,"lastX":693.5,"lastY":820,"backgroundColor":"#05aee6","iconColor":"#f5f5f5","borderColor":"#0d7db5"},{"title":"Main Components of the Linux Kernel","id":"3","desc":"Key components that make up the Linux kernel.","bgType":"rect","icon":"file","fx":933.5,"fy":300,"type":"node","index":6,"x":933.5,"y":300,"vy":0,"vx":0,"lastX":693.5,"lastY":340,"backgroundColor":"#05aee6","iconColor":"#f5f5f5","borderColor":"#0d7db5"},{"title":"Process Management","id":"3.1","desc":"How the Linux kernel manages processes.","bgType":"rect","icon":"file","fx":773.5,"fy":500,"type":"node","index":7,"x":773.5,"y":500,"vy":0,"vx":0,"lastX":693.5,"lastY":580,"backgroundColor":"#05aee6","iconColor":"#f5f5f5","borderColor":"#0d7db5"},{"title":"Scheduling","id":"3.1.1","desc":"Techniques and algorithms for scheduling processes.","bgType":"rect","icon":"file","fx":773.5,"fy":700,"type":"node","index":8,"x":773.5,"y":700,"vy":0,"vx":0,"lastX":613.5,"lastY":820,"backgroundColor":"#05aee6","iconColor":"#f5f5f5","borderColor":"#0d7db5"},{"title":"System Calls","id":"3.1.2","desc":"Interface between user applications and the kernel.","bgType":"rect","icon":"file","fx":1013.5,"fy":700,"type":"node","index":9,"x":1013.5,"y":700,"vy":0,"vx":0,"lastX":1173.5,"lastY":820,"backgroundColor":"#05aee6","iconColor":"#f5f5f5","borderColor":"#0d7db5"},{"title":"Memory Management","id":"3.2","desc":"Management of memory resources by the Linux kernel.","bgType":"rect","icon":"file","fx":1013.5,"fy":500,"type":"node","index":10,"x":1013.5,"y":500,"vy":0,"vx":0,"lastX":1253.5,"lastY":580,"backgroundColor":"#05aee6","iconColor":"#f5f5f5","borderColor":"#0d7db5"},{"title":"Virtual Memory","id":"3.2.1","desc":"Concept of virtual memory and its implementation.","bgType":"rect","icon":"file","fx":693.5,"fy":700,"type":"node","index":11,"x":693.5,"y":700,"vy":0,"vx":0,"lastX":773.5,"lastY":820,"backgroundColor":"#05aee6","iconColor":"#f5f5f5","borderColor":"#0d7db5"},{"title":"Physical Memory","id":"3.2.2","desc":"Management of physical memory.","bgType":"rect","icon":"file","fx":1093.5,"fy":700,"type":"node","index":12,"x":1093.5,"y":700,"vy":0,"vx":0,"lastX":853.5,"lastY":820,"backgroundColor":"#05aee6","iconColor":"#f5f5f5","borderColor":"#0d7db5"},{"title":"File Systems","id":"3.3","desc":"Handling of file systems by the Linux kernel.","bgType":"rect","icon":"file","fx":693.5,"fy":500,"type":"node","index":13,"x":693.5,"y":500,"vy":0,"vx":0,"lastX":293.5,"lastY":580,"backgroundColor":"#05aee6","iconColor":"#f5f5f5","borderColor":"#0d7db5"},{"title":"VFS (Virtual File System)","id":"3.3.1","desc":"Abstraction layer that provides a common interface to different file systems.","bgType":"rect","icon":"file","fx":613.5,"fy":700,"type":"node","index":14,"x":613.5,"y":700,"vy":0,"vx":0,"lastX":933.5,"lastY":820,"backgroundColor":"#05aee6","iconColor":"#f5f5f5","borderColor":"#0d7db5"},{"title":"Device Drivers","id":"3.4","desc":"Software modules that allow the kernel to interact with hardware devices.","bgType":"rect","icon":"file","fx":1093.5,"fy":500,"type":"node","index":15,"x":1093.5,"y":500,"vy":0,"vx":0,"lastX":773.5,"lastY":580,"backgroundColor":"#05aee6","iconColor":"#f5f5f5","borderColor":"#0d7db5"},{"title":"Network Management","id":"3.5","desc":"Management of networking functionalities by the Linux kernel.","bgType":"rect","icon":"file","fx":613.5,"fy":500,"type":"node","index":16,"x":613.5,"y":500,"vy":0,"vx":0,"lastX":1013.5,"lastY":580,"backgroundColor":"#05aee6","iconColor":"#f5f5f5","borderColor":"#0d7db5"},{"title":"Socket Interface","id":"3.5.1","desc":"API for network communication.","bgType":"rect","icon":"file","fx":1173.5,"fy":700,"type":"node","index":17,"x":1173.5,"y":700,"vy":0,"vx":0,"lastX":1093.5,"lastY":820,"backgroundColor":"#05aee6","iconColor":"#f5f5f5","borderColor":"#0d7db5"},{"title":"Security Management","id":"3.6","desc":"Security features and mechanisms in the Linux kernel.","bgType":"rect","icon":"file","fx":1173.5,"fy":500,"type":"node","index":18,"x":1173.5,"y":500,"vy":0,"vx":0,"lastX":613.5,"lastY":580,"backgroundColor":"#05aee6","iconColor":"#f5f5f5","borderColor":"#0d7db5"},{"title":"Security Modules","id":"3.6.1","desc":"Loadable kernel modules for enhancing security (e.g., SELinux).","bgType":"rect","icon":"file","fx":533.5,"fy":700,"type":"node","index":19,"x":533.5,"y":700,"vy":0,"vx":0,"lastX":533.5,"lastY":820,"backgroundColor":"#05aee6","iconColor":"#f5f5f5","borderColor":"#0d7db5"},{"title":"Kernel Development","id":"4","desc":"Overview of Linux kernel development process.","bgType":"rect","icon":"file","fx":773.5,"fy":300,"type":"node","index":20,"x":773.5,"y":300,"vy":0,"vx":0,"lastX":853.5,"lastY":340,"backgroundColor":"#05aee6","iconColor":"#f5f5f5","borderColor":"#0d7db5"},{"title":"Versioning","id":"4.1","desc":"Understanding the versioning scheme of the Linux kernel.","bgType":"rect","icon":"file","fx":533.5,"fy":500,"type":"node","index":21,"x":533.5,"y":500,"vy":0,"vx":0,"lastX":1413.5,"lastY":580,"backgroundColor":"#05aee6","iconColor":"#f5f5f5","borderColor":"#0d7db5"},{"title":"Contribution Process","id":"4.2","desc":"How to contribute to the Linux kernel development.","bgType":"rect","icon":"file","fx":1253.5,"fy":500,"type":"node","index":22,"x":1253.5,"y":500,"vy":0,"vx":0,"lastX":1333.5,"lastY":580,"backgroundColor":"#05aee6","iconColor":"#f5f5f5","borderColor":"#0d7db5"},{"title":"Compilation and Building","id":"5","desc":"Steps to compile and build the Linux kernel.","bgType":"rect","icon":"file","fx":1013.5,"fy":300,"type":"node","index":23,"x":1013.5,"y":300,"vy":0,"vx":0,"lastX":1013.5,"lastY":340,"backgroundColor":"#05aee6","iconColor":"#f5f5f5","borderColor":"#0d7db5"},{"title":"Configuration","id":"5.1","desc":"Configuring the kernel options before building.","bgType":"rect","icon":"file","fx":453.5,"fy":500,"type":"node","index":24,"x":453.5,"y":500,"vy":0,"vx":0,"lastX":853.5,"lastY":580,"backgroundColor":"#05aee6","iconColor":"#f5f5f5","borderColor":"#0d7db5"},{"title":"Building","id":"5.2","desc":"Compiling and building the kernel from source.","bgType":"rect","icon":"file","fx":1333.5,"fy":500,"type":"node","index":25,"x":1333.5,"y":500,"vy":0,"vx":0,"lastX":453.5,"lastY":580,"backgroundColor":"#05aee6","iconColor":"#f5f5f5","borderColor":"#0d7db5"},{"title":"Installation","id":"5.3","desc":"Installing the newly built kernel.","bgType":"rect","icon":"file","fx":373.5,"fy":500,"type":"node","index":26,"x":373.5,"y":500,"vy":0,"vx":0,"lastX":933.5,"lastY":580,"backgroundColor":"#05aee6","iconColor":"#f5f5f5","borderColor":"#0d7db5"},{"title":"Kernel Debugging","id":"6","desc":"Techniques and tools for debugging the Linux kernel.","bgType":"rect","icon":"file","fx":693.5,"fy":300,"type":"node","index":27,"x":693.5,"y":300,"vy":0,"vx":0,"lastX":933.5,"lastY":340,"backgroundColor":"#05aee6","iconColor":"#f5f5f5","borderColor":"#0d7db5"},{"title":"Logging","id":"6.1","desc":"Using kernel logs for debugging purposes.","bgType":"rect","icon":"file","fx":1413.5,"fy":500,"type":"node","index":28,"x":1413.5,"y":500,"vy":0,"vx":0,"lastX":1093.5,"lastY":580,"backgroundColor":"#05aee6","iconColor":"#f5f5f5","borderColor":"#0d7db5"},{"title":"Debugging Tools","id":"6.2","desc":"Tools such as gdb, ftrace, and perf for kernel debugging.","bgType":"rect","icon":"file","fx":293.5,"fy":500,"type":"node","index":29,"x":293.5,"y":500,"vy":0,"vx":0,"lastX":373.5,"lastY":580,"backgroundColor":"#05aee6","iconColor":"#f5f5f5","borderColor":"#0d7db5"}],"links":[{"source":"2.2","target":"2.2.2","id":"0LXLV7letcKtszCfJizmYxeh","x1":null,"y1":null,"x2":null,"y2":null,"type":"line","startIndex":1,"endIndex":3,"index":0},{"source":"3","target":"3.2","id":"0Wi1re55Z7YgvaEqOSM5obzK","x1":null,"y1":null,"x2":null,"y2":null,"type":"line","startIndex":1,"endIndex":3,"index":1},{"source":"4","target":"4.2","id":"1Q9Ad5p0mqhzSlyj2gUclvWL","x1":null,"y1":null,"x2":null,"y2":null,"type":"line","startIndex":1,"endIndex":3,"index":2},{"source":"1","target":"2","id":"8qPccx6pvCvKaw2vr1b1LVX4","x1":null,"y1":null,"x2":null,"y2":null,"type":"line","startIndex":1,"endIndex":3,"index":3},{"source":"3","target":"3.1","id":"9JemVAu6RjoiJIh4ZCsjbpR9","x1":null,"y1":null,"x2":null,"y2":null,"type":"line","startIndex":1,"endIndex":3,"index":4},{"source":"1","target":"6","id":"EBAEbqDuu4clGhkGiO2aRGE9","x1":null,"y1":null,"x2":null,"y2":null,"type":"line","startIndex":1,"endIndex":3,"index":5},{"source":"4","target":"4.1","id":"K7V4PR63amMClQHknIWmOxM4","x1":null,"y1":null,"x2":null,"y2":null,"type":"line","startIndex":1,"endIndex":3,"index":6},{"source":"3.3","target":"3.3.1","id":"KwI28blTMCuaccCejqS4Sp3a","x1":null,"y1":null,"x2":null,"y2":null,"type":"line","startIndex":1,"endIndex":3,"index":7},{"source":"3.1","target":"3.1.2","id":"L99PK9leoF4nBzVNh5IkVdo3","x1":null,"y1":null,"x2":null,"y2":null,"type":"line","startIndex":1,"endIndex":3,"index":8},{"source":"2","target":"2.2","id":"OcAF61vBDbV66UIARybm9St7","x1":null,"y1":null,"x2":null,"y2":null,"type":"line","startIndex":1,"endIndex":3,"index":9},{"source":"3","target":"3.5","id":"RXRVPwet8jpg7zZU3cRt9Vvi","x1":null,"y1":null,"x2":null,"y2":null,"type":"line","startIndex":1,"endIndex":3,"index":10},{"source":"3.1","target":"3.1.1","id":"RoWqZThSO7CBffjHD2ExJZbE","x1":null,"y1":null,"x2":null,"y2":null,"type":"line","startIndex":1,"endIndex":3,"index":11},{"source":"3.5","target":"3.5.1","id":"SEZn5GJ0p8VqePsSTgtobpYJ","x1":null,"y1":null,"x2":null,"y2":null,"type":"line","startIndex":1,"endIndex":3,"index":12},{"source":"6","target":"6.2","id":"VFK4TwWXD8EEJwiW6b6JjztJ","x1":null,"y1":null,"x2":null,"y2":null,"type":"line","startIndex":1,"endIndex":3,"index":13},{"source":"3.6","target":"3.6.1","id":"Xaz3YDY4hG2cuK0PRiZsOhEP","x1":null,"y1":null,"x2":null,"y2":null,"type":"line","startIndex":1,"endIndex":3,"index":14},{"source":"1","target":"5","id":"XlIJOt6oY14kY3jyzy1kB9tT","x1":null,"y1":null,"x2":null,"y2":null,"type":"line","startIndex":1,"endIndex":3,"index":15},{"source":"2.2","target":"2.2.1","id":"dUnL6XJHE69hDZtJpsVDMdJ9","x1":null,"y1":null,"x2":null,"y2":null,"type":"line","startIndex":1,"endIndex":3,"index":16},{"source":"5","target":"5.1","id":"dZbKfPyTNfMldJbyjUBIrP3r","x1":null,"y1":null,"x2":null,"y2":null,"type":"line","startIndex":1,"endIndex":3,"index":17},{"source":"3","target":"3.4","id":"dlZh3WLpLwPsMi2c2Mgf1cc6","x1":null,"y1":null,"x2":null,"y2":null,"type":"line","startIndex":1,"endIndex":3,"index":18},{"source":"5","target":"5.2","id":"eegjD7WcqGB7VeUJ5jzCVZR9","x1":null,"y1":null,"x2":null,"y2":null,"type":"line","startIndex":1,"endIndex":3,"index":19},{"source":"2","target":"2.1","id":"f0Z5qI2kVrMQ6V0eDqT6ikFI","x1":null,"y1":null,"x2":null,"y2":null,"type":"line","startIndex":1,"endIndex":3,"index":20},{"source":"3.2","target":"3.2.1","id":"g5GSn0bTGTmxSIpd7fGARAze","x1":null,"y1":null,"x2":null,"y2":null,"type":"line","startIndex":1,"endIndex":3,"index":21},{"source":"3","target":"3.3","id":"gasWopka9NIjIkmgPfqrU2r9","x1":null,"y1":null,"x2":null,"y2":null,"type":"line","startIndex":1,"endIndex":3,"index":22},{"source":"3.2","target":"3.2.2","id":"mLeWryTcwn1vGgPuKmWTzBiW","x1":null,"y1":null,"x2":null,"y2":null,"type":"line","startIndex":1,"endIndex":3,"index":23},{"source":"6","target":"6.1","id":"pGmyCWeEhwoUnlW2urf6XYY6","x1":null,"y1":null,"x2":null,"y2":null,"type":"line","startIndex":1,"endIndex":3,"index":24},{"source":"1","target":"3","id":"r3PHMfOrnvf5oE06OLl54tRf","x1":null,"y1":null,"x2":null,"y2":null,"type":"line","startIndex":1,"endIndex":3,"index":25},{"source":"3","target":"3.6","id":"x04pPqFs4rumbVE1F4wOa00o","x1":null,"y1":null,"x2":null,"y2":null,"type":"line","startIndex":1,"endIndex":3,"index":26},{"source":"1","target":"4","id":"xp09NmW1RMomU6BvtNVKykE4","x1":null,"y1":null,"x2":null,"y2":null,"type":"line","startIndex":1,"endIndex":3,"index":27},{"source":"5","target":"5.3","id":"yjpdzivFoVn7hlI8Zemasvmo","x1":null,"y1":null,"x2":null,"y2":null,"type":"line","startIndex":1,"endIndex":3,"index":28}],"config":[{"key":"arrowEnd","value":true},{"key":"connectType","value":"straight"},{"key":"connectionPointFixed","value":true},{"key":"iconDiameter","value":50},{"key":"iconFillColor","value":"#05aee6"},{"key":"iconTitleNumber","value":7},{"key":"lineType","value":"dotted"},{"key":"nodeBgType","value":"circle"},{"key":"nodeBorderColor","value":"#0d7db5"},{"key":"nodeIcon","value":"coord"},{"key":"nodeIconColor","value":"#f5f5f5"},{"key":"pathAnimateType","value":"none"},{"key":"strokeColor","value":"#7d8604"},{"key":"strokeWidth","value":1},{"key":"textAlignType","value":"middle"}]}